google/cloud/dataplex/__init__.py
google/cloud/dataplex/gapic_version.py
google/cloud/dataplex/py.typed
google/cloud/dataplex_v1/__init__.py
google/cloud/dataplex_v1/gapic_metadata.json
google/cloud/dataplex_v1/gapic_version.py
google/cloud/dataplex_v1/py.typed
google/cloud/dataplex_v1/services/__init__.py
google/cloud/dataplex_v1/services/business_glossary_service/__init__.py
google/cloud/dataplex_v1/services/business_glossary_service/async_client.py
google/cloud/dataplex_v1/services/business_glossary_service/client.py
google/cloud/dataplex_v1/services/business_glossary_service/pagers.py
google/cloud/dataplex_v1/services/business_glossary_service/transports/__init__.py
google/cloud/dataplex_v1/services/business_glossary_service/transports/base.py
google/cloud/dataplex_v1/services/business_glossary_service/transports/grpc.py
google/cloud/dataplex_v1/services/business_glossary_service/transports/grpc_asyncio.py
google/cloud/dataplex_v1/services/business_glossary_service/transports/rest.py
google/cloud/dataplex_v1/services/business_glossary_service/transports/rest_base.py
google/cloud/dataplex_v1/services/catalog_service/__init__.py
google/cloud/dataplex_v1/services/catalog_service/async_client.py
google/cloud/dataplex_v1/services/catalog_service/client.py
google/cloud/dataplex_v1/services/catalog_service/pagers.py
google/cloud/dataplex_v1/services/catalog_service/transports/__init__.py
google/cloud/dataplex_v1/services/catalog_service/transports/base.py
google/cloud/dataplex_v1/services/catalog_service/transports/grpc.py
google/cloud/dataplex_v1/services/catalog_service/transports/grpc_asyncio.py
google/cloud/dataplex_v1/services/catalog_service/transports/rest.py
google/cloud/dataplex_v1/services/catalog_service/transports/rest_base.py
google/cloud/dataplex_v1/services/cmek_service/__init__.py
google/cloud/dataplex_v1/services/cmek_service/async_client.py
google/cloud/dataplex_v1/services/cmek_service/client.py
google_cloud_dataplex-2.13.0.dist-info/licenses/LICENSE
google_cloud_dataplex-2.13.0.dist-info/METADATA
google_cloud_dataplex-2.13.0.dist-info/WHEEL
google_cloud_dataplex-2.13.0.dist-info/top_level.txt
google_cloud_dataplex-2.13.0.dist-info/RECORD
